[
  {
    "line": 1,
    "elements": [
      {
        "start_timestamp": "2021-07-21T16:54:59.893Z",
        "before": [
          {
            "result": {
              "duration": 2055446000,
              "status": "passed"
            },
            "match": {
              "location": "steps.Hook.InitializeTest(io.cucumber.java.Scenario)"
            }
          }
        ],
        "line": 4,
        "name": "Login with correct username and password",
        "description": "",
        "id": "loginfeature;login-with-correct-username-and-password",
        "after": [
          {
            "result": {
              "duration": 71538000,
              "status": "passed"
            },
            "match": {
              "location": "steps.Hook.TearDownTest(io.cucumber.java.Scenario)"
            }
          }
        ],
        "type": "scenario",
        "keyword": "Scenario",
        "steps": [
          {
            "result": {
              "duration": 1072832000,
              "status": "passed"
            },
            "before": [
              {
                "result": {
                  "duration": 1119000,
                  "status": "passed"
                },
                "match": {
                  "location": "steps.Hook.BeforeEveryStep(io.cucumber.java.Scenario)"
                }
              }
            ],
            "line": 5,
            "name": "I navigate to the login page",
            "match": {
              "location": "steps.LoginStep.iNavigateToTheLoginPage()"
            },
            "after": [
              {
                "result": {
                  "duration": 220000,
                  "status": "passed"
                },
                "match": {
                  "location": "steps.Hook.AfterEveryStep(io.cucumber.java.Scenario)"
                }
              }
            ],
            "keyword": "Given "
          },
          {
            "result": {
              "duration": 159078000,
              "status": "passed"
            },
            "before": [
              {
                "result": {
                  "duration": 151000,
                  "status": "passed"
                },
                "match": {
                  "location": "steps.Hook.BeforeEveryStep(io.cucumber.java.Scenario)"
                }
              }
            ],
            "line": 6,
            "name": "I enter the following for Login",
            "match": {
              "location": "steps.LoginStep.iEnterTheFollowingForLogin(java.util.List\u003csteps.LoginStep$User\u003e)"
            },
            "after": [
              {
                "result": {
                  "duration": 145000,
                  "status": "passed"
                },
                "match": {
                  "location": "steps.Hook.AfterEveryStep(io.cucumber.java.Scenario)"
                }
              }
            ],
            "rows": [
              {
                "cells": [
                  "username",
                  "password"
                ]
              },
              {
                "cells": [
                  "admin",
                  "adminpassword"
                ]
              }
            ],
            "keyword": "And "
          },
          {
            "result": {
              "duration": 129324000,
              "status": "passed"
            },
            "before": [
              {
                "result": {
                  "duration": 604000,
                  "status": "passed"
                },
                "match": {
                  "location": "steps.Hook.BeforeEveryStep(io.cucumber.java.Scenario)"
                }
              }
            ],
            "line": 9,
            "name": "I click login button",
            "match": {
              "location": "steps.LoginStep.iClickLoginButton()"
            },
            "after": [
              {
                "result": {
                  "duration": 136000,
                  "status": "passed"
                },
                "match": {
                  "location": "steps.Hook.AfterEveryStep(io.cucumber.java.Scenario)"
                }
              }
            ],
            "keyword": "And "
          },
          {
            "result": {
              "duration": 38248000,
              "status": "passed"
            },
            "before": [
              {
                "result": {
                  "duration": 129000,
                  "status": "passed"
                },
                "match": {
                  "location": "steps.Hook.BeforeEveryStep(io.cucumber.java.Scenario)"
                }
              }
            ],
            "line": 10,
            "name": "I should see the userform page",
            "match": {
              "location": "steps.LoginStep.iShouldSeeTheUserformPage()"
            },
            "after": [
              {
                "result": {
                  "duration": 148000,
                  "status": "passed"
                },
                "match": {
                  "location": "steps.Hook.AfterEveryStep(io.cucumber.java.Scenario)"
                }
              }
            ],
            "keyword": "Then "
          }
        ]
      },
      {
        "start_timestamp": "2021-07-21T16:55:03.450Z",
        "before": [
          {
            "result": {
              "duration": 251544000,
              "status": "passed"
            },
            "match": {
              "location": "steps.Hook.InitializeTest(io.cucumber.java.Scenario)"
            }
          }
        ],
        "line": 12,
        "name": "Login with correct username and password to fail",
        "description": "",
        "id": "loginfeature;login-with-correct-username-and-password-to-fail",
        "after": [
          {
            "result": {
              "duration": 66073000,
              "status": "passed"
            },
            "match": {
              "location": "steps.Hook.TearDownTest(io.cucumber.java.Scenario)"
            }
          }
        ],
        "type": "scenario",
        "keyword": "Scenario",
        "steps": [
          {
            "result": {
              "duration": 435390000,
              "status": "passed"
            },
            "before": [
              {
                "result": {
                  "duration": 910000,
                  "status": "passed"
                },
                "match": {
                  "location": "steps.Hook.BeforeEveryStep(io.cucumber.java.Scenario)"
                }
              }
            ],
            "line": 13,
            "name": "I navigate to the login page",
            "match": {
              "location": "steps.LoginStep.iNavigateToTheLoginPage()"
            },
            "after": [
              {
                "result": {
                  "duration": 148000,
                  "status": "passed"
                },
                "match": {
                  "location": "steps.Hook.AfterEveryStep(io.cucumber.java.Scenario)"
                }
              }
            ],
            "keyword": "Given "
          },
          {
            "result": {
              "duration": 112453000,
              "status": "passed"
            },
            "before": [
              {
                "result": {
                  "duration": 135000,
                  "status": "passed"
                },
                "match": {
                  "location": "steps.Hook.BeforeEveryStep(io.cucumber.java.Scenario)"
                }
              }
            ],
            "line": 14,
            "name": "I enter the following for Login",
            "match": {
              "location": "steps.LoginStep.iEnterTheFollowingForLogin(java.util.List\u003csteps.LoginStep$User\u003e)"
            },
            "after": [
              {
                "result": {
                  "duration": 135000,
                  "status": "passed"
                },
                "match": {
                  "location": "steps.Hook.AfterEveryStep(io.cucumber.java.Scenario)"
                }
              }
            ],
            "rows": [
              {
                "cells": [
                  "username",
                  "password"
                ]
              },
              {
                "cells": [
                  "admin",
                  "adminpassword"
                ]
              }
            ],
            "keyword": "And "
          },
          {
            "result": {
              "duration": 103132000,
              "status": "passed"
            },
            "before": [
              {
                "result": {
                  "duration": 157000,
                  "status": "passed"
                },
                "match": {
                  "location": "steps.Hook.BeforeEveryStep(io.cucumber.java.Scenario)"
                }
              }
            ],
            "line": 17,
            "name": "I click login button",
            "match": {
              "location": "steps.LoginStep.iClickLoginButton()"
            },
            "after": [
              {
                "result": {
                  "duration": 161000,
                  "status": "passed"
                },
                "match": {
                  "location": "steps.Hook.AfterEveryStep(io.cucumber.java.Scenario)"
                }
              }
            ],
            "keyword": "And "
          },
          {
            "result": {
              "duration": 289000,
              "status": "passed"
            },
            "before": [
              {
                "result": {
                  "duration": 150000,
                  "status": "passed"
                },
                "match": {
                  "location": "steps.Hook.BeforeEveryStep(io.cucumber.java.Scenario)"
                }
              }
            ],
            "line": 18,
            "name": "I should see the userform page wrongly",
            "match": {
              "location": "steps.LoginStep.iShouldSeeTheUserformPageWrongly()"
            },
            "after": [
              {
                "result": {
                  "duration": 145000,
                  "status": "passed"
                },
                "match": {
                  "location": "steps.Hook.AfterEveryStep(io.cucumber.java.Scenario)"
                }
              }
            ],
            "keyword": "Then "
          }
        ]
      }
    ],
    "name": "LoginFeature",
    "description": "  This feature deals with the login functionality of the applications",
    "id": "loginfeature",
    "keyword": "Feature",
    "uri": "file:src/test/java/features/Login.feature",
    "tags": []
  }
]